pytorch_pqrnn/__init__.py
pytorch_pqrnn/dataset.py
pytorch_pqrnn/model.py
pytorch_pqrnn/utils.py
pytorch_pqrnn-0.1.0.dist-info/entry_points.txt
pytorch_pqrnn-0.1.0.dist-info/LICENSE
pytorch_pqrnn-0.1.0.dist-info/WHEEL
pytorch_pqrnn-0.1.0.dist-info/METADATA
pytorch_pqrnn-0.1.0.dist-info/RECORD
