Metadata-Version: 2.1
Name: pytorch-pqrnn
Version: 0.1.0
Summary: Pytorch implementation of pQRNN
Home-page: https://github.com/ChenghaoMou/pytorch-pqrnn
License: MIT
Author: pytorch-pqrnn
Author-email: mouchenghao@gmail.com
Requires-Python: >=3.7,<4.0
Classifier: Development Status :: 3 - Alpha
Classifier: Intended Audience :: Developers
Classifier: License :: OSI Approved :: MIT License
Classifier: Operating System :: OS Independent
Classifier: Programming Language :: Python :: 3
Classifier: Programming Language :: Python :: 3.7
Classifier: Programming Language :: Python :: 3.8
Classifier: Programming Language :: Python :: 3.9
Classifier: Topic :: Software Development :: Libraries :: Python Modules
Requires-Dist: bandit (>=1.7.0,<2.0.0)
Requires-Dist: bitstring (>=3.1.7,<4.0.0)
Requires-Dist: datasets (>=1.4.1,<2.0.0)
Requires-Dist: importlib_metadata (>=1.6.0,<2.0.0); python_version < "3.8"
Requires-Dist: mmh3 (>=2.5.1,<3.0.0)
Requires-Dist: nltk (>=3.5,<4.0)
Requires-Dist: numpy (>=1.19.2,<2.0.0)
Requires-Dist: pandas (>=1.1.3,<2.0.0)
Requires-Dist: pyhash (>=0.9.3,<0.10.0)
Requires-Dist: pytorch-lightning (>=0.10.0,<0.11.0)
Requires-Dist: rich (>=8.0.0,<9.0.0)
Requires-Dist: scikit-learn (>=0.23.2,<0.24.0)
Requires-Dist: torch (==1.7.1)
Requires-Dist: typer[all] (>=0.3.2,<0.4.0)
Project-URL: Repository, https://github.com/ChenghaoMou/pytorch-pqrnn
